.gitignore
MANIFEST.in
README.rst
bootstrap.py
buildout.cfg
setup.cfg
setup.py
collective/__init__.py
collective.swfobject.egg-info/PKG-INFO
collective.swfobject.egg-info/SOURCES.txt
collective.swfobject.egg-info/dependency_links.txt
collective.swfobject.egg-info/entry_points.txt
collective.swfobject.egg-info/namespace_packages.txt
collective.swfobject.egg-info/not-zip-safe
collective.swfobject.egg-info/requires.txt
collective.swfobject.egg-info/top_level.txt
collective/swfobject/__init__.py
collective/swfobject/configure.zcml
collective/swfobject/expressInstall.swf
collective/swfobject/swfobject.js
collective/swfobject/tests.py
collective/swfobject/profiles/default/jsregistry.xml
collective/swfobject/profiles/default/metadata.xml
docs/HISTORY.txt
docs/INSTALL.txt
docs/LICENSE.GPL
docs/LICENSE.txt