Metadata-Version: 1.0
Name: collective.swfobject
Version: 1.0
Summary: SWFObject for Plone
Home-page: https://github.com/collective/collective.swfobject
Author: JeanMichel FRANCOIS aka toutpt
Author-email: toutpt@gmail.com
License: GPL
Platform: UNKNOWN
Classifier: Framework :: Plone
Classifier: Programming Language :: Python
